LICENSE
MANIFEST.in
README.rst
dot_parser.py
pydot.py
setup.py
pydot2.egg-info/PKG-INFO
pydot2.egg-info/SOURCES.txt
pydot2.egg-info/dependency_links.txt
pydot2.egg-info/requires.txt
pydot2.egg-info/top_level.txt